attachments/__init__.py
attachments/admin.py
attachments/apps.py
attachments/forms.py
attachments/models.py
attachments/urls.py
attachments/views.py
attachments/locale/README.transifex
attachments/locale/da/LC_MESSAGES/django.po
attachments/locale/de/LC_MESSAGES/django.po
attachments/locale/el/LC_MESSAGES/django.po
attachments/locale/en/LC_MESSAGES/django.po
attachments/locale/es_AR/LC_MESSAGES/django.po
attachments/locale/fi/LC_MESSAGES/django.po
attachments/locale/fr/LC_MESSAGES/django.po
attachments/locale/it/LC_MESSAGES/django.po
attachments/locale/pt_BR/LC_MESSAGES/django.po
attachments/locale/ru/LC_MESSAGES/django.po
attachments/management/__init__.py
attachments/management/commands/__init__.py
attachments/management/commands/delete_stale_attachments.py
attachments/migrations/0001_initial.py
attachments/migrations/0002_auto_20180104_1247.py
attachments/migrations/0003_auto_20190722_1216.py
attachments/migrations/0004_db_index.py
attachments/migrations/0005_object_id_charfield.py
attachments/migrations/__init__.py
attachments/templates/attachments/add.html
attachments/templates/attachments/add_form.html
attachments/templates/attachments/base.html
attachments/templates/attachments/delete_link.html
attachments/templatetags/__init__.py
attachments/templatetags/attachments_tags.py
attachments/tests/__init__.py
attachments/tests/base.py
attachments/tests/test_integrity.py
attachments/tests/test_template.py
attachments/tests/test_views.py
attachments/tests/testapp/__init__.py
attachments/tests/testapp/admin.py
attachments/tests/testapp/apps.py
attachments/tests/testapp/models.py
attachments/tests/testapp/settings.py
attachments/tests/testapp/urls.py
attachments/tests/testapp/migrations/0001_initial.py
attachments/tests/testapp/migrations/0002_auto_20180104_1247.py
attachments/tests/testapp/migrations/0003_model_with_uuid_pk.py
attachments/tests/testapp/migrations/__init__.py
attachments/tests/testapp/templates/testmodel_detail.html
django_attachments-1.12.dist-info/LICENSE
django_attachments-1.12.dist-info/METADATA
django_attachments-1.12.dist-info/WHEEL
django_attachments-1.12.dist-info/top_level.txt
django_attachments-1.12.dist-info/RECORD
