Metadata-Version: 2.2
Name: django-attachments
Version: 1.12
Summary: django-attachments is generic Django application to attach Files (Attachments) to any model.
Home-page: https://github.com/bartTC/django-attachments
Author: Martin Mahner
Author-email: martin@mahner.org
License: MIT
Keywords: django,attachments,files,upload
Classifier: Development Status :: 5 - Production/Stable
Classifier: Environment :: Web Environment
Classifier: Intended Audience :: Developers
Classifier: License :: OSI Approved :: MIT License
Classifier: Operating System :: OS Independent
Classifier: Programming Language :: Python
Classifier: Programming Language :: Python :: 2.7
Classifier: Programming Language :: Python :: 3.4
Classifier: Programming Language :: Python :: 3.5
Classifier: Programming Language :: Python :: 3.6
Classifier: Programming Language :: Python :: 3.7
Classifier: Framework :: Django
License-File: LICENSE
Requires-Dist: django>=1.11
Requires-Dist: six
Requires-Dist: mock
Provides-Extra: test
Requires-Dist: pytest; extra == "test"
Requires-Dist: pytest-cov; extra == "test"
Requires-Dist: pytest-django; extra == "test"
Requires-Dist: pytest-flakes; extra == "test"
